{
"rozdzial_0.md": "chapter_0.md",
  "rozdzial_1.md": "chapter_1.md",
  "rozdzial_2.md": "chapter_2.md",
  "rozdzial_3.md": "chapter_3.md",
  "rozdzial_4.md": "chapter_4.md",
  "rozdzial_5.md": "chapter_5.md",
  "rozdzial_6.md": "chapter_6.md",
  "rozdz.10.md": "chapter_10.md",
  "rozdz.11.md": "chapter_11.md",
  "rozdz.12.md": "chapter_12.md",
  "rozdz.13.md": "chapter_13.md",
  "rozdz.7.md": "chapter_7.md",
  "rozdz.8.md": "chapter_8.md",
"rozdz.9.md": "chapter_9.md",
"rozdział 9 test emp.md": "chapter_9_test_emp.md",
"Glossary.md": "Glossary.md",
"Aneks do roz.4.md": "appendix_4.md",
"Aneks do roz.5.md": "appendix_5.md",
"AneksA_Symbols.md": "appendix_A_symbols.md",
"AneksB_Derivation-of-c.md": "appendix_B_derivation-of-c.md",
"AneksC_Topological-origin.md": "appendix_C_topological-origin.md",
"AneksD_Electrodynamics.md": "appendix_D_electrodynamics.md",
"AneksE_Reverse-Eng.md": "appendix_E_reverse-eng.md",
"wstep.md": "intro.md"
}